WikiScraper/__init__.py
WikiScraper/__main__.py
WikiScraper/stop_lists/__init__.py
WikiScraper/stop_lists/english.txt
WikiScraper_dustpole-1.1.dist-info/LICENSE
WikiScraper_dustpole-1.1.dist-info/METADATA
WikiScraper_dustpole-1.1.dist-info/WHEEL
WikiScraper_dustpole-1.1.dist-info/top_level.txt
WikiScraper_dustpole-1.1.dist-info/RECORD
