Metadata-Version: 2.1
Name: WikiScraper_dustpole
Version: 1.1
Summary: Create a word-list from a scraped webpage.
Author-email: Dustin Pollreis <dustpole@gmail.com>
Project-URL: Homepage, https://github.com/dustpole/WikiScraper
Project-URL: Issues, https://github.com/dustpole/WikiScraper/issues
Project-URL: Repository, https://github.com/dustpole/WikiScraper.git
Classifier: Programming Language :: Python :: 3
Classifier: License :: OSI Approved :: MIT License
Classifier: Operating System :: OS Independent
Requires-Python: >=3.10
License-File: LICENSE
Requires-Dist: requests
Requires-Dist: beautifulsoup4
Requires-Dist: pathlib
